Iris_trm/Box.py
Iris_trm/Fonts.py
Iris_trm/Gradient.py
Iris_trm/Iris.py
Iris_trm/Loading.py
Iris_trm/Logger.py
Iris_trm/MenuHorizontal.py
Iris_trm/Table.py
Iris_trm/__init__.py
Iris_trm-1.0.0.dist-info/METADATA
Iris_trm-1.0.0.dist-info/WHEEL
Iris_trm-1.0.0.dist-info/top_level.txt
Iris_trm-1.0.0.dist-info/RECORD
